pyexpsolver/__init__.py
pyexpsolver-0.0.13.dist-info/LICENSE
pyexpsolver-0.0.13.dist-info/METADATA
pyexpsolver-0.0.13.dist-info/WHEEL
pyexpsolver-0.0.13.dist-info/top_level.txt
pyexpsolver-0.0.13.dist-info/RECORD
