Metadata-Version: 2.1
Name: pyexpsolver
Version: 0.0.13
Summary: Automatically solve algebraic expression
Home-page: https://github.com/albertocastronovo/pyexpsolver
Author: Alberto Castronovo
Author-email: alberto.castronovo@hotmail.it
License: UNKNOWN
Platform: UNKNOWN
Classifier: Programming Language :: Python :: 3
Classifier: License :: OSI Approved :: MIT License
Classifier: Operating System :: OS Independent
Requires-Python: >=3.6
